argnorm/__init__.py
argnorm/argnorm_version.py
argnorm/atomicwrite.py
argnorm/cli.py
argnorm/drug_categorization.py
argnorm/lib.py
argnorm/normalize.py
argnorm/normalizers.py
argnorm/data/argannot_ARO_mapping.tsv
argnorm/data/aro.obo
argnorm/data/deeparg_ARO_mapping.tsv
argnorm/data/groot_ARO_mapping.tsv
argnorm/data/megares_ARO_mapping.tsv
argnorm/data/ncbi_ARO_mapping.tsv
argnorm/data/resfinder_ARO_mapping.tsv
argnorm/data/resfinderfg_ARO_mapping.tsv
argnorm/data/sarg_ARO_mapping.tsv
argnorm/data/manual_curation/argannot_curation.tsv
argnorm/data/manual_curation/deeparg_curation.tsv
argnorm/data/manual_curation/groot_curation.tsv
argnorm/data/manual_curation/megares_curation.tsv
argnorm/data/manual_curation/ncbi_curation.tsv
argnorm/data/manual_curation/resfinder_curation.tsv
argnorm/data/manual_curation/resfinderfg_curation.tsv
argnorm/data/manual_curation/sarg_curation.tsv
argnorm-1.1.0.dist-info/licenses/LICENSE
argnorm-1.1.0.dist-info/METADATA
argnorm-1.1.0.dist-info/WHEEL
argnorm-1.1.0.dist-info/entry_points.txt
argnorm-1.1.0.dist-info/top_level.txt
argnorm-1.1.0.dist-info/RECORD
