Metadata-Version: 2.4
Name: argnorm
Version: 1.1.0
Summary: Normalize antibiotic resistance genes (ARGs) results by using the ARO ontology (developed by CARD).
Author-email: ArgNorm Developers <luispedro@big-data-biology.org>
License: MIT
Project-URL: Homepage, https://github.com/BigDataBiology/argNorm
Keywords: bioinformatics,antibiotic-resistance,ontology
Classifier: Topic :: Scientific/Engineering :: Bio-Informatics
Classifier: Programming Language :: Python :: 3.7
Classifier: Programming Language :: Python :: 3.8
Classifier: Programming Language :: Python :: 3.9
Classifier: Programming Language :: Python :: 3.10
Classifier: Programming Language :: Python :: 3.11
Classifier: Programming Language :: Python :: 3.12
Classifier: Programming Language :: Python :: 3.13
Classifier: Development Status :: 5 - Production/Stable
Classifier: Operating System :: OS Independent
Classifier: Natural Language :: English
Requires-Python: >=3.7
License-File: LICENSE
Requires-Dist: pandas
Requires-Dist: pronto
Provides-Extra: dev
Requires-Dist: pytest; extra == "dev"
Dynamic: license-file
